GLXCurses/Actionable.py
GLXCurses/Adjustment.py
GLXCurses/Application.py
GLXCurses/Bin.py
GLXCurses/Bindings.py
GLXCurses/Box.py
GLXCurses/Button.py
GLXCurses/Buzzer.py
GLXCurses/CheckButton.py
GLXCurses/Constants.py
GLXCurses/Container.py
GLXCurses/Editable.py
GLXCurses/Entry.py
GLXCurses/EntryBuffer.py
GLXCurses/EntryCompletion.py
GLXCurses/EventBusBkp.py
GLXCurses/EventBusClient.py
GLXCurses/EventLoop.py
GLXCurses/Frame.py
GLXCurses/HBox.py
GLXCurses/HSeparator.py
GLXCurses/Label.py
GLXCurses/MainLoop.py
GLXCurses/MenuBar.py
GLXCurses/MessageBar.py
GLXCurses/Misc.py
GLXCurses/Object.py
GLXCurses/ProgressBar.py
GLXCurses/RadioButton.py
GLXCurses/Range.py
GLXCurses/Scrollable.py
GLXCurses/StatusBar.py
GLXCurses/Style.py
GLXCurses/ToolBar.py
GLXCurses/Utils.py
GLXCurses/VBox.py
GLXCurses/VSeparator.py
GLXCurses/Widget.py
GLXCurses/Window.py
GLXCurses/__init__.py
galaxie_curses-0.2.dist-info/METADATA
galaxie_curses-0.2.dist-info/RECORD
galaxie_curses-0.2.dist-info/WHEEL
galaxie_curses-0.2.dist-info/top_level.txt
