Metadata-Version: 2.1
Name: galaxie-curses
Version: 0.2
Summary: Galaxie Curses is a free software ToolKit for the NCurses API
Home-page: https://gitlab.com/Tuuux/galaxie-curses
Author: Tuuux
Author-email: tuxa@rtnp.org
License: GPL
Platform: UNKNOWN
